processamento_imagens_py/__init__.py
processamento_imagens_py/processamento/__init__.py
processamento_imagens_py/processamento/combinacao.py
processamento_imagens_py/processamento/transformacao.py
processamento_imagens_py/utils/__init__.py
processamento_imagens_py/utils/io.py
processamento_imagens_py/utils/plot.py
processamento_imagens_py-0.0.1.dist-info/METADATA
processamento_imagens_py-0.0.1.dist-info/WHEEL
processamento_imagens_py-0.0.1.dist-info/top_level.txt
processamento_imagens_py-0.0.1.dist-info/RECORD
